<Patients>

    <patient>

        <patientId>1</patientId>

        <patientName>aSOzuAdtIq</patientName>

        <city>Kolkata</city>

        <age>54</age>

    </patient>

    <patient>

        <patientId>2</patientId>

        <patientName>uetwiUTQDj</patientName>

        <city>Kolkata</city>

        <age>65</age>

    </patient>

    <patient>

        <patientId>6</patientId>

        <patientName>llbvaoqwHv</patientName>

        <city>Kolkata</city>

        <age>69</age>

    </patient>

    <patient>

        <patientId>8</patientId>

        <patientName>urAtuJxpNj</patientName>

        <city>Kolkata</city>

        <age>44</age>

    </patient>

    <patient>

        <patientId>12</patientId>

        <patientName>chIssKWuxo</patientName>

        <city>Kolkata</city>

        <age>77</age>

    </patient>

    <patient>

        <patientId>17</patientId>

        <patientName>PJMylUjzuE</patientName>

        <city>Kolkata</city>

        <age>44</age>

    </patient>

    <patient>

        <patientId>20</patientId>

        <patientName>JQpFNhcXGd</patientName>

        <city>Kolkata</city>

        <age>49</age>

    </patient>

    <patient>

        <patientId>21</patientId>

        <patientName>yVoPBOcLRv</patientName>

        <city>Kolkata</city>

        <age>80</age>

    </patient>

    <patient>

        <patientId>24</patientId>

        <patientName>AZWDlVZNgl</patientName>

        <city>Kolkata</city>

        <age>19</age>

    </patient>

    <patient>

        <patientId>27</patientId>

        <patientName>SQNLqASptz</patientName>

        <city>Kolkata</city>

        <age>16</age>

    </patient>

    <patient>

        <patientId>28</patientId>

        <patientName>OCFxMaNGGN</patientName>

        <city>Kolkata</city>

        <age>49</age>

    </patient>

    <patient>

        <patientId>30</patientId>

        <patientName>MNYgYzeqpC</patientName>

        <city>Kolkata</city>

        <age>74</age>

    </patient>

    <patient>

        <patientId>31</patientId>

        <patientName>DAIIfQxwRR</patientName>

        <city>Kolkata</city>

        <age>72</age>

    </patient>

    <patient>

        <patientId>33</patientId>

        <patientName>EOKjuxFUFt</patientName>

        <city>Kolkata</city>

        <age>11</age>

    </patient>

    <patient>

        <patientId>34</patientId>

        <patientName>VwAIcuQWRm</patientName>

        <city>Kolkata</city>

        <age>64</age>

    </patient>

    <patient>

        <patientId>36</patientId>

        <patientName>nqNzntcCmS</patientName>

        <city>Kolkata</city>

        <age>61</age>

    </patient>

    </Patients>